catalight/__init__.py
catalight/catalight_GUI.py
catalight/cl_tools.py
catalight/config.py
catalight/analysis/__init__.py
catalight/analysis/chromatogram_scanner_gui.py
catalight/analysis/gcdata.py
catalight/analysis/irdata.py
catalight/analysis/make_empty_cal_expt.py
catalight/analysis/plotting.py
catalight/analysis/run_calibration.py
catalight/analysis/run_change_xdata.py
catalight/analysis/run_initial_analysis.py
catalight/analysis/run_plot_chromatograms_stacked.py
catalight/analysis/run_plot_comparison.py
catalight/analysis/tools.py
catalight/analysis/user_inputs.py
catalight/equipment/__init__.py
catalight/equipment/alicat_connection_tester.py
catalight/equipment/experiment_control.py
catalight/equipment/gc_delay_tester.py
catalight/equipment/run_diode_calibration.py
catalight/equipment/gas_control/__init__.py
catalight/equipment/gas_control/alicat.py
catalight/equipment/gas_control/template.py
catalight/equipment/gc_control/__init__.py
catalight/equipment/gc_control/peaksimple_control_demo.py
catalight/equipment/gc_control/sri_gc.py
catalight/equipment/gc_control/template.py
catalight/equipment/heating/__init__.py
catalight/equipment/heating/template.py
catalight/equipment/heating/watlow.py
catalight/equipment/light_sources/__init__.py
catalight/equipment/light_sources/diode_control.py
catalight/equipment/light_sources/nkt_analyze_calibration.py
catalight/equipment/light_sources/nkt_collect_calibration.py
catalight/equipment/light_sources/nkt_helper_funcs.py
catalight/equipment/light_sources/nkt_system.py
catalight/equipment/light_sources/nkt_verify_calibration.py
catalight/equipment/light_sources/template.py
catalight/equipment/power_meter/__init__.py
catalight/equipment/power_meter/newport.py
catalight-0.2.0.dist-info/LICENSE
catalight-0.2.0.dist-info/METADATA
catalight-0.2.0.dist-info/WHEEL
catalight-0.2.0.dist-info/top_level.txt
catalight-0.2.0.dist-info/RECORD
