Metadata-Version: 2.1
Name: catalight
Version: 0.2.0
Summary: Photoreactor system automation, data handling, and analysis.
Author-email: Briley Bourgeois <bbourge6@stanford.edu>, Claire Carlin <cccarlin@stanford.edu>
Project-URL: Homepage, https://github.com/Dionne-Lab/catalight
Project-URL: Bug Tracker, https://github.com/Dionne-Lab/catalight/issues
Classifier: Programming Language :: Python :: 3
Classifier: License :: OSI Approved :: MIT License
Classifier: Operating System :: OS Independent
Requires-Python: >=3.7
License-File: LICENSE
Requires-Dist: alicat ==0.4.0
Requires-Dist: matplotlib >=3.5.3
Requires-Dist: mcculw >=1.0.0
Requires-Dist: numpy >=1.21
Requires-Dist: pandas >=1.4.4
Requires-Dist: psutil >=5.9.0
Requires-Dist: pycaw >=20191226
Requires-Dist: pyqtgraph >=0.11.0
Requires-Dist: scipy >=1.9.1
Requires-Dist: pyserial >=3.5
Requires-Dist: pyttsx3 >=2.90
Requires-Dist: comtypes >=1.1.10
Requires-Dist: pythonnet >=2.5.2
Requires-Dist: pywatlow >=0.1.3
Requires-Dist: sphinx ==5.0.2
Requires-Dist: sphinx-rtd-theme >=0.4.3
Requires-Dist: nkt-tools >=0.0.1
Requires-Dist: PyQt5
Requires-Dist: pywin32 >=302 ; platform_system == "Windows"
